dermoscopic_symmetry
