Metadata-Version: 2.1
Name: dermoscopic-symmetry
Version: 0.0.2
Summary: A package to study skin lesion's symmetry and help diagnose diseases like menalomas.
Home-page: https://github.com/GalakVince/dermoscopic_symmetry
Author: Vincent Toureau
Author-email: Vincent.Toureau@grenoble-inp.org
License: UNKNOWN
Platform: UNKNOWN
Classifier: Programming Language :: Python :: 3
Classifier: License :: OSI Approved :: MIT License
Classifier: Operating System :: OS Independent
